kak_pishetsya.py
kak_pishetsya-0.0.1.dev0.dist-info/METADATA
kak_pishetsya-0.0.1.dev0.dist-info/WHEEL
kak_pishetsya-0.0.1.dev0.dist-info/RECORD
